yolopandas/__init__.py
yolopandas/chains.py
yolopandas/llm_accessor.py
yolopandas/utils/__init__.py
yolopandas/utils/query_helpers.py
yolopandas-0.0.6.dist-info/LICENSE
yolopandas-0.0.6.dist-info/METADATA
yolopandas-0.0.6.dist-info/WHEEL
yolopandas-0.0.6.dist-info/RECORD
