Metadata-Version: 2.1
Name: yolopandas
Version: 0.0.6
Summary: Interact with Pandas objects via LLMs and langchain.
Home-page: https://www.github.com/ccurme/yolopandas
License: MIT
Requires-Python: >=3.9,<4.0
Classifier: License :: OSI Approved :: MIT License
Classifier: Programming Language :: Python :: 3
Classifier: Programming Language :: Python :: 3.9
Classifier: Programming Language :: Python :: 3.10
Classifier: Programming Language :: Python :: 3.11
Requires-Dist: ipython (>=8.8.0,<9.0.0)
Requires-Dist: langchain (>=0.0.60,<1)
Requires-Dist: openai (>=0,<1)
Requires-Dist: pandas (>=1.4,<2.0)
Project-URL: Repository, https://www.github.com/ccurme/yolopandas
